disneypluspy.py
disneypluspy-1.0.0.dist-info/METADATA
disneypluspy-1.0.0.dist-info/WHEEL
disneypluspy-1.0.0.dist-info/top_level.txt
disneypluspy-1.0.0.dist-info/RECORD
