Metadata-Version: 2.1
Name: disneypluspy
Version: 1.0.0
Summary: Checker.
Author-email: Pandaxyz-xd <contact@tourble.org>
Project-URL: Homepage, https://github.com/Pandaxyz-xd/disneypluspy
Project-URL: Bug Tracker, https://github.com/Pandaxyz-xd/disneypluspy/issues
Classifier: Programming Language :: Python :: 3
Classifier: License :: OSI Approved :: MIT License
Classifier: Operating System :: OS Independent
Requires-Python: >=3.7
